{"participant":{"name":"김혜린","studentId":"20231371","handedness":"right","timestamp":"2025-11-25T05:11:11.278Z"},"deviceInfo":{"screenWidth":393,"screenHeight":852,"viewportWidth":393,"viewportHeight":671,"devicePixelRatio":3,"userAgent":"Mozilla/5.0 (iPhone; CPU iPhone OS 18_4_1 like Mac OS X) AppleWebKit/605.1.15 (KHTML, like Gecko) Mobile/15E148 Safari/604.1 Safari/604.1 KAKAOTALK/25.10.1 (INAPP) KAKAOTALK/25.10.1 (INAPP)"},"calibration":{"reachablePoints":308,"points":[{"x":94,"y":494,"reachable":true,"timestamp":1764047497488},{"x":73,"y":480,"reachable":true,"timestamp":1764047497567},{"x":67,"y":475,"reachable":true,"timestamp":1764047497584},{"x":62,"y":468,"reachable":true,"timestamp":1764047497601},{"x":57,"y":460,"reachable":true,"timestamp":1764047497617},{"x":53,"y":453,"reachable":true,"timestamp":1764047497633},{"x":51,"y":444,"reachable":true,"timestamp":1764047497650},{"x":49,"y":435,"reachable":true,"timestamp":1764047497667},{"x":48,"y":423,"reachable":true,"timestamp":1764047497684},{"x":46,"y":411,"reachable":true,"timestamp":1764047497700},{"x":46,"y":401,"reachable":true,"timestamp":1764047497717},{"x":46,"y":389,"reachable":true,"timestamp":1764047497733},{"x":46,"y":373,"reachable":true,"timestamp":1764047497750},{"x":46,"y":352,"reachable":true,"timestamp":1764047497767},{"x":47,"y":332,"reachable":true,"timestamp":1764047497783},{"x":50,"y":314,"reachable":true,"timestamp":1764047497800},{"x":55,"y":297,"reachable":true,"timestamp":1764047497817},{"x":61,"y":280,"reachable":true,"timestamp":1764047497833},{"x":71,"y":262,"reachable":true,"timestamp":1764047497850},{"x":85,"y":245,"reachable":true,"timestamp":1764047497867},{"x":101,"y":231,"reachable":true,"timestamp":1764047497883},{"x":115,"y":220,"reachable":true,"timestamp":1764047497900},{"x":126,"y":209,"reachable":true,"timestamp":1764047497916},{"x":142,"y":194,"reachable":true,"timestamp":1764047497933},{"x":171,"y":172,"reachable":true,"timestamp":1764047497949},{"x":206,"y":147,"reachable":true,"timestamp":1764047497966},{"x":234,"y":130,"reachable":true,"timestamp":1764047497983},{"x":258,"y":122,"reachable":true,"timestamp":1764047498001},{"x":284,"y":115,"reachable":true,"timestamp":1764047498016},{"x":312,"y":112,"reachable":true,"timestamp":1764047498033},{"x":334,"y":110,"reachable":true,"timestamp":1764047498050},{"x":345,"y":110,"reachable":true,"timestamp":1764047498066},{"x":348,"y":110,"reachable":true,"timestamp":1764047498083},{"x":349,"y":112,"reachable":true,"timestamp":1764047498100},{"x":351,"y":113,"reachable":true,"timestamp":1764047498116},{"x":351,"y":114,"reachable":true,"timestamp":1764047498133},{"x":353,"y":114,"reachable":true,"timestamp":1764047498149},{"x":355,"y":115,"reachable":true,"timestamp":1764047498166},{"x":357,"y":115,"reachable":true,"timestamp":1764047498182},{"x":359,"y":115,"reachable":true,"timestamp":1764047498199},{"x":360,"y":116,"reachable":true,"timestamp":1764047498216},{"x":363,"y":117,"reachable":true,"timestamp":1764047498232},{"x":367,"y":118,"reachable":true,"timestamp":1764047498249},{"x":371,"y":119,"reachable":true,"timestamp":1764047498266},{"x":374,"y":121,"reachable":true,"timestamp":1764047498282},{"x":378,"y":121,"reachable":true,"timestamp":1764047498299},{"x":381,"y":121,"reachable":true,"timestamp":1764047498316},{"x":384,"y":121,"reachable":true,"timestamp":1764047498333},{"x":386,"y":121,"reachable":true,"timestamp":1764047498349},{"x":386,"y":122,"reachable":true,"timestamp":1764047498366},{"x":378,"y":124,"reachable":true,"timestamp":1764047498382},{"x":363,"y":127,"reachable":true,"timestamp":1764047498399},{"x":343,"y":130,"reachable":true,"timestamp":1764047498416},{"x":320,"y":137,"reachable":true,"timestamp":1764047498432},{"x":284,"y":152,"reachable":true,"timestamp":1764047498450},{"x":228,"y":181,"reachable":true,"timestamp":1764047498466},{"x":169,"y":221,"reachable":true,"timestamp":1764047498482},{"x":121,"y":269,"reachable":true,"timestamp":1764047498499},{"x":97,"y":314,"reachable":true,"timestamp":1764047498515},{"x":90,"y":348,"reachable":true,"timestamp":1764047498532},{"x":86,"y":380,"reachable":true,"timestamp":1764047498549},{"x":86,"y":411,"reachable":true,"timestamp":1764047498565},{"x":86,"y":438,"reachable":true,"timestamp":1764047498582},{"x":89,"y":460,"reachable":true,"timestamp":1764047498599},{"x":95,"y":475,"reachable":true,"timestamp":1764047498615},{"x":98,"y":485,"reachable":true,"timestamp":1764047498632},{"x":100,"y":490,"reachable":true,"timestamp":1764047498648},{"x":102,"y":494,"reachable":true,"timestamp":1764047498665},{"x":104,"y":498,"reachable":true,"timestamp":1764047498682},{"x":107,"y":502,"reachable":true,"timestamp":1764047498698},{"x":109,"y":505,"reachable":true,"timestamp":1764047498715},{"x":110,"y":505,"reachable":true,"timestamp":1764047498732},{"x":110,"y":502,"reachable":true,"timestamp":1764047498765},{"x":109,"y":492,"reachable":true,"timestamp":1764047498782},{"x":108,"y":471,"reachable":true,"timestamp":1764047498798},{"x":109,"y":432,"reachable":true,"timestamp":1764047498815},{"x":115,"y":392,"reachable":true,"timestamp":1764047498832},{"x":127,"y":352,"reachable":true,"timestamp":1764047498848},{"x":144,"y":310,"reachable":true,"timestamp":1764047498865},{"x":176,"y":257,"reachable":true,"timestamp":1764047498882},{"x":217,"y":206,"reachable":true,"timestamp":1764047498898},{"x":263,"y":170,"reachable":true,"timestamp":1764047498915},{"x":301,"y":146,"reachable":true,"timestamp":1764047498931},{"x":323,"y":136,"reachable":true,"timestamp":1764047498948},{"x":337,"y":131,"reachable":true,"timestamp":1764047498964},{"x":346,"y":130,"reachable":true,"timestamp":1764047498981},{"x":354,"y":129,"reachable":true,"timestamp":1764047498998},{"x":358,"y":129,"reachable":true,"timestamp":1764047499014},{"x":363,"y":129,"reachable":true,"timestamp":1764047499031},{"x":369,"y":129,"reachable":true,"timestamp":1764047499048},{"x":376,"y":129,"reachable":true,"timestamp":1764047499064},{"x":374,"y":129,"reachable":true,"timestamp":1764047499114},{"x":371,"y":129,"reachable":true,"timestamp":1764047499130},{"x":368,"y":130,"reachable":true,"timestamp":1764047499148},{"x":363,"y":131,"reachable":true,"timestamp":1764047499164},{"x":352,"y":137,"reachable":true,"timestamp":1764047499181},{"x":318,"y":153,"reachable":true,"timestamp":1764047499197},{"x":250,"y":191,"reachable":true,"timestamp":1764047499214},{"x":184,"y":245,"reachable":true,"timestamp":1764047499231},{"x":127,"y":314,"reachable":true,"timestamp":1764047499248},{"x":103,"y":428,"reachable":true,"timestamp":1764047501431},{"x":96,"y":423,"reachable":true,"timestamp":1764047501443},{"x":93,"y":406,"reachable":true,"timestamp":1764047501460},{"x":92,"y":393,"reachable":true,"timestamp":1764047501477},{"x":92,"y":376,"reachable":true,"timestamp":1764047501477},{"x":98,"y":338,"reachable":true,"timestamp":1764047501493},{"x":115,"y":293,"reachable":true,"timestamp":1764047501510},{"x":138,"y":251,"reachable":true,"timestamp":1764047501527},{"x":160,"y":219,"reachable":true,"timestamp":1764047501544},{"x":181,"y":196,"reachable":true,"timestamp":1764047501560},{"x":206,"y":175,"reachable":true,"timestamp":1764047501577},{"x":236,"y":157,"reachable":true,"timestamp":1764047501594},{"x":260,"y":146,"reachable":true,"timestamp":1764047501610},{"x":274,"y":143,"reachable":true,"timestamp":1764047501627},{"x":286,"y":141,"reachable":true,"timestamp":1764047501644},{"x":302,"y":137,"reachable":true,"timestamp":1764047501660},{"x":319,"y":132,"reachable":true,"timestamp":1764047501677},{"x":332,"y":128,"reachable":true,"timestamp":1764047501693},{"x":338,"y":125,"reachable":true,"timestamp":1764047501710},{"x":339,"y":125,"reachable":true,"timestamp":1764047501727},{"x":333,"y":126,"reachable":true,"timestamp":1764047501743},{"x":311,"y":135,"reachable":true,"timestamp":1764047501760},{"x":271,"y":157,"reachable":true,"timestamp":1764047501777},{"x":235,"y":186,"reachable":true,"timestamp":1764047501793},{"x":198,"y":225,"reachable":true,"timestamp":1764047501810},{"x":151,"y":277,"reachable":true,"timestamp":1764047501826},{"x":110,"y":342,"reachable":true,"timestamp":1764047501843},{"x":88,"y":407,"reachable":true,"timestamp":1764047501860},{"x":87,"y":448,"reachable":true,"timestamp":1764047501876},{"x":88,"y":472,"reachable":true,"timestamp":1764047501893},{"x":90,"y":484,"reachable":true,"timestamp":1764047501910},{"x":92,"y":486,"reachable":true,"timestamp":1764047501926},{"x":97,"y":486,"reachable":true,"timestamp":1764047501943},{"x":101,"y":473,"reachable":true,"timestamp":1764047501960},{"x":110,"y":445,"reachable":true,"timestamp":1764047501976},{"x":126,"y":400,"reachable":true,"timestamp":1764047501993},{"x":152,"y":345,"reachable":true,"timestamp":1764047502011},{"x":188,"y":290,"reachable":true,"timestamp":1764047502026},{"x":234,"y":245,"reachable":true,"timestamp":1764047502043},{"x":273,"y":220,"reachable":true,"timestamp":1764047502060},{"x":289,"y":210,"reachable":true,"timestamp":1764047502076},{"x":304,"y":202,"reachable":true,"timestamp":1764047502093},{"x":319,"y":195,"reachable":true,"timestamp":1764047502109},{"x":329,"y":189,"reachable":true,"timestamp":1764047502126},{"x":333,"y":188,"reachable":true,"timestamp":1764047502142},{"x":333,"y":190,"reachable":true,"timestamp":1764047502159},{"x":321,"y":202,"reachable":true,"timestamp":1764047502176},{"x":282,"y":234,"reachable":true,"timestamp":1764047502193},{"x":232,"y":282,"reachable":true,"timestamp":1764047502209},{"x":191,"y":336,"reachable":true,"timestamp":1764047502226},{"x":159,"y":392,"reachable":true,"timestamp":1764047502242},{"x":139,"y":446,"reachable":true,"timestamp":1764047502259},{"x":135,"y":478,"reachable":true,"timestamp":1764047502276},{"x":135,"y":488,"reachable":true,"timestamp":1764047502293},{"x":135,"y":493,"reachable":true,"timestamp":1764047502309},{"x":134,"y":496,"reachable":true,"timestamp":1764047502326},{"x":133,"y":497,"reachable":true,"timestamp":1764047502343},{"x":132,"y":497,"reachable":true,"timestamp":1764047502359},{"x":132,"y":491,"reachable":true,"timestamp":1764047502392},{"x":138,"y":475,"reachable":true,"timestamp":1764047502409},{"x":151,"y":427,"reachable":true,"timestamp":1764047502426},{"x":173,"y":361,"reachable":true,"timestamp":1764047502442},{"x":207,"y":292,"reachable":true,"timestamp":1764047502459},{"x":262,"y":234,"reachable":true,"timestamp":1764047502476},{"x":318,"y":191,"reachable":true,"timestamp":1764047502492},{"x":351,"y":172,"reachable":true,"timestamp":1764047502509},{"x":363,"y":168,"reachable":true,"timestamp":1764047502526},{"x":377,"y":168,"reachable":true,"timestamp":1764047502542},{"x":384,"y":168,"reachable":true,"timestamp":1764047502559},{"x":381,"y":168,"reachable":true,"timestamp":1764047502608},{"x":375,"y":171,"reachable":true,"timestamp":1764047502625},{"x":358,"y":184,"reachable":true,"timestamp":1764047502642},{"x":309,"y":229,"reachable":true,"timestamp":1764047502659},{"x":249,"y":301,"reachable":true,"timestamp":1764047502675},{"x":213,"y":371,"reachable":true,"timestamp":1764047502692},{"x":195,"y":421,"reachable":true,"timestamp":1764047502709},{"x":186,"y":464,"reachable":true,"timestamp":1764047502725},{"x":182,"y":501,"reachable":true,"timestamp":1764047502742},{"x":181,"y":522,"reachable":true,"timestamp":1764047502759},{"x":179,"y":530,"reachable":true,"timestamp":1764047502776},{"x":177,"y":532,"reachable":true,"timestamp":1764047502792},{"x":175,"y":532,"reachable":true,"timestamp":1764047502808},{"x":175,"y":527,"reachable":true,"timestamp":1764047502825},{"x":175,"y":516,"reachable":true,"timestamp":1764047502842},{"x":180,"y":492,"reachable":true,"timestamp":1764047502858},{"x":196,"y":438,"reachable":true,"timestamp":1764047502875},{"x":224,"y":378,"reachable":true,"timestamp":1764047502892},{"x":258,"y":330,"reachable":true,"timestamp":1764047502908},{"x":288,"y":290,"reachable":true,"timestamp":1764047502925},{"x":309,"y":266,"reachable":true,"timestamp":1764047502942},{"x":319,"y":256,"reachable":true,"timestamp":1764047502958},{"x":323,"y":253,"reachable":true,"timestamp":1764047502975},{"x":325,"y":253,"reachable":true,"timestamp":1764047502991},{"x":325,"y":259,"reachable":true,"timestamp":1764047503008},{"x":311,"y":280,"reachable":true,"timestamp":1764047503025},{"x":278,"y":330,"reachable":true,"timestamp":1764047503041},{"x":248,"y":393,"reachable":true,"timestamp":1764047503058},{"x":230,"y":446,"reachable":true,"timestamp":1764047503075},{"x":219,"y":487,"reachable":true,"timestamp":1764047503091},{"x":214,"y":516,"reachable":true,"timestamp":1764047503108},{"x":214,"y":527,"reachable":true,"timestamp":1764047503125},{"x":214,"y":531,"reachable":true,"timestamp":1764047503141},{"x":214,"y":527,"reachable":true,"timestamp":1764047503174},{"x":214,"y":518,"reachable":true,"timestamp":1764047503191},{"x":218,"y":486,"reachable":true,"timestamp":1764047503208},{"x":235,"y":427,"reachable":true,"timestamp":1764047503225},{"x":258,"y":364,"reachable":true,"timestamp":1764047503241},{"x":285,"y":308,"reachable":true,"timestamp":1764047503258},{"x":316,"y":264,"reachable":true,"timestamp":1764047503274},{"x":342,"y":237,"reachable":true,"timestamp":1764047503291},{"x":359,"y":226,"reachable":true,"timestamp":1764047503307},{"x":370,"y":224,"reachable":true,"timestamp":1764047503323},{"x":374,"y":224,"reachable":true,"timestamp":1764047503340},{"x":367,"y":237,"reachable":true,"timestamp":1764047503373},{"x":338,"y":273,"reachable":true,"timestamp":1764047503390},{"x":305,"y":331,"reachable":true,"timestamp":1764047503406},{"x":289,"y":392,"reachable":true,"timestamp":1764047503424},{"x":286,"y":442,"reachable":true,"timestamp":1764047503440},{"x":287,"y":477,"reachable":true,"timestamp":1764047503457},{"x":289,"y":503,"reachable":true,"timestamp":1764047503473},{"x":290,"y":526,"reachable":true,"timestamp":1764047503490},{"x":292,"y":544,"reachable":true,"timestamp":1764047503506},{"x":294,"y":552,"reachable":true,"timestamp":1764047503523},{"x":295,"y":552,"reachable":true,"timestamp":1764047503540},{"x":295,"y":537,"reachable":true,"timestamp":1764047503557},{"x":295,"y":498,"reachable":true,"timestamp":1764047503573},{"x":296,"y":453,"reachable":true,"timestamp":1764047503590},{"x":301,"y":412,"reachable":true,"timestamp":1764047503606},{"x":310,"y":379,"reachable":true,"timestamp":1764047503623},{"x":322,"y":347,"reachable":true,"timestamp":1764047503640},{"x":338,"y":315,"reachable":true,"timestamp":1764047503656},{"x":354,"y":290,"reachable":true,"timestamp":1764047503673},{"x":364,"y":282,"reachable":true,"timestamp":1764047503690},{"x":366,"y":281,"reachable":true,"timestamp":1764047503707},{"x":366,"y":282,"reachable":true,"timestamp":1764047503756},{"x":362,"y":296,"reachable":true,"timestamp":1764047503772},{"x":353,"y":332,"reachable":true,"timestamp":1764047503789},{"x":342,"y":388,"reachable":true,"timestamp":1764047503806},{"x":339,"y":440,"reachable":true,"timestamp":1764047503823},{"x":341,"y":478,"reachable":true,"timestamp":1764047503840},{"x":349,"y":501,"reachable":true,"timestamp":1764047503857},{"x":355,"y":513,"reachable":true,"timestamp":1764047503873},{"x":358,"y":519,"reachable":true,"timestamp":1764047503890},{"x":359,"y":523,"reachable":true,"timestamp":1764047503906},{"x":359,"y":515,"reachable":true,"timestamp":1764047503939},{"x":351,"y":489,"reachable":true,"timestamp":1764047503956},{"x":344,"y":454,"reachable":true,"timestamp":1764047503973},{"x":344,"y":430,"reachable":true,"timestamp":1764047503989},{"x":350,"y":415,"reachable":true,"timestamp":1764047504006},{"x":356,"y":396,"reachable":true,"timestamp":1764047504023},{"x":359,"y":369,"reachable":true,"timestamp":1764047504039},{"x":361,"y":343,"reachable":true,"timestamp":1764047504056},{"x":363,"y":338,"reachable":true,"timestamp":1764047504072},{"x":363,"y":340,"reachable":true,"timestamp":1764047504090},{"x":363,"y":349,"reachable":true,"timestamp":1764047504107},{"x":364,"y":369,"reachable":true,"timestamp":1764047504122},{"x":365,"y":406,"reachable":true,"timestamp":1764047504140},{"x":367,"y":443,"reachable":true,"timestamp":1764047504155},{"x":371,"y":474,"reachable":true,"timestamp":1764047504172},{"x":376,"y":500,"reachable":true,"timestamp":1764047504189},{"x":381,"y":515,"reachable":true,"timestamp":1764047504206},{"x":383,"y":521,"reachable":true,"timestamp":1764047504223},{"x":385,"y":523,"reachable":true,"timestamp":1764047504239},{"x":386,"y":525,"reachable":true,"timestamp":1764047504256},{"x":386,"y":529,"reachable":true,"timestamp":1764047504273},{"x":386,"y":533,"reachable":true,"timestamp":1764047504289},{"x":366,"y":538,"reachable":true,"timestamp":1764047504306},{"x":332,"y":538,"reachable":true,"timestamp":1764047504323},{"x":299,"y":522,"reachable":true,"timestamp":1764047504339},{"x":275,"y":503,"reachable":true,"timestamp":1764047504356},{"x":261,"y":488,"reachable":true,"timestamp":1764047504372},{"x":255,"y":477,"reachable":true,"timestamp":1764047504389},{"x":253,"y":469,"reachable":true,"timestamp":1764047504405},{"x":253,"y":468,"reachable":true,"timestamp":1764047504422},{"x":255,"y":468,"reachable":true,"timestamp":1764047504438},{"x":261,"y":474,"reachable":true,"timestamp":1764047504456},{"x":269,"y":493,"reachable":true,"timestamp":1764047504472},{"x":270,"y":525,"reachable":true,"timestamp":1764047504489},{"x":270,"y":561,"reachable":true,"timestamp":1764047504505},{"x":270,"y":585,"reachable":true,"timestamp":1764047504522},{"x":270,"y":589,"reachable":true,"timestamp":1764047504539},{"x":270,"y":581,"reachable":true,"timestamp":1764047504556},{"x":260,"y":553,"reachable":true,"timestamp":1764047504572},{"x":254,"y":528,"reachable":true,"timestamp":1764047504589},{"x":252,"y":501,"reachable":true,"timestamp":1764047504605},{"x":256,"y":461,"reachable":true,"timestamp":1764047504621},{"x":268,"y":409,"reachable":true,"timestamp":1764047504639},{"x":286,"y":355,"reachable":true,"timestamp":1764047504655},{"x":306,"y":309,"reachable":true,"timestamp":1764047504671},{"x":330,"y":271,"reachable":true,"timestamp":1764047504689},{"x":350,"y":248,"reachable":true,"timestamp":1764047504705},{"x":353,"y":245,"reachable":true,"timestamp":1764047504721},{"x":348,"y":245,"reachable":true,"timestamp":1764047504755},{"x":338,"y":260,"reachable":true,"timestamp":1764047504771},{"x":317,"y":299,"reachable":true,"timestamp":1764047504788},{"x":300,"y":346,"reachable":true,"timestamp":1764047504805},{"x":293,"y":388,"reachable":true,"timestamp":1764047504821},{"x":293,"y":416,"reachable":true,"timestamp":1764047504838},{"x":297,"y":437,"reachable":true,"timestamp":1764047504855},{"x":302,"y":449,"reachable":true,"timestamp":1764047504872},{"x":305,"y":453,"reachable":true,"timestamp":1764047504887},{"x":306,"y":453,"reachable":true,"timestamp":1764047504905},{"x":300,"y":452,"reachable":true,"timestamp":1764047504921},{"x":279,"y":419,"reachable":true,"timestamp":1764047504938},{"x":264,"y":369,"reachable":true,"timestamp":1764047504954},{"x":261,"y":318,"reachable":true,"timestamp":1764047504971},{"x":262,"y":275,"reachable":true,"timestamp":1764047504988},{"x":264,"y":248,"reachable":true,"timestamp":1764047505006}]},"circleData":{"handedness":"right","centroid":{"x":250.3896103896104,"y":335.8474025974026},"circleCenter":{"x":350,"y":700},"circleCenterType":"fixed-iphone16","radius":488.87217143134666,"radiusCalculationMethod":"70th percentile of calibration distances","radiusPoint":{"x":50,"y":314,"reachable":true,"timestamp":1764047497800},"maxDistance":590.2169092799697,"farthestPoint":{"x":334,"y":110,"reachable":true,"timestamp":1764047498050},"borderThreshold":122.21804285783666,"borderRange":{"min":366.65412857351,"max":488.87217143134666},"angleRange":"180-270° (9-12 o'clock)","angleRangeDegrees":{"min":180,"max":270}},"experiments":[{"condition":"fixed","order":1,"avgCompletionTime":2615.5,"errorRate":0.2,"trials":[{"trial":1,"targetString":"vie","userInput":"vir","buttonPosition":{"x":299,"y":5,"zone":"top-right-fixed","generationMethod":"fixed-top-right","details":null},"buttonTouchPosition":{"x":336,"y":46},"completionTime":3075,"typingTime":1785,"error":true},{"trial":2,"targetString":"die","userInput":"die","buttonPosition":{"x":299,"y":5,"zone":"top-right-fixed","generationMethod":"fixed-top-right","details":null},"buttonTouchPosition":{"x":343,"y":53},"completionTime":3122,"typingTime":1652,"error":false},{"trial":3,"targetString":"tie","userInput":"tie","buttonPosition":{"x":299,"y":5,"zone":"top-right-fixed","generationMethod":"fixed-top-right","details":null},"buttonTouchPosition":{"x":332,"y":42},"completionTime":2491,"typingTime":1984,"error":false},{"trial":4,"targetString":"sue","userInput":"sue","buttonPosition":{"x":299,"y":5,"zone":"top-right-fixed","generationMethod":"fixed-top-right","details":null},"buttonTouchPosition":{"x":335,"y":44},"completionTime":2491,"typingTime":1784,"error":false},{"trial":5,"targetString":"cue","userInput":"cue","buttonPosition":{"x":299,"y":5,"zone":"top-right-fixed","generationMethod":"fixed-top-right","details":null},"buttonTouchPosition":{"x":331,"y":41},"completionTime":2358,"typingTime":1518,"error":false}]},{"condition":"adaptive","order":2,"avgCompletionTime":3072.25,"errorRate":0.2,"trials":[{"trial":1,"targetString":"woe","userInput":"woe","buttonPosition":{"x":75,"y":370,"zone":"adaptive-circle-border-angle","generationMethod":"adaptive-circle-border-angle-from-calibration","details":{"handedness":"right","circleCenter":{"x":350,"y":700},"radius":488.87217143134666,"radiusCalculationMethod":"70th percentile","radiusPoint":{"x":50,"y":314,"reachable":true,"timestamp":1764047497800},"maxDistance":590.2169092799697,"farthestPoint":{"x":334,"y":110,"reachable":true,"timestamp":1764047498050},"borderThreshold":195.54886857253868,"minBorderDistance":293.323302858808,"maxBorderDistance":527.9819451458544,"selectedBorderPoint":{"x":115,"y":392},"selectedPointDistance":387.4132160884551,"selectedPointAngle":232.65683873864037,"preferredAngleSegment":{"min":180,"max":207.5},"usedSegmentPoints":false,"attemptsToAvoidPrevious":1,"minDistanceFromPrevious":80,"allowedAngleRange":"180-270° (9-12 o'clock)","totalReachablePoints":308,"totalBorderPoints":161,"angleFilteredBorderPoints":161,"validBorderPoints":160}},"buttonTouchPosition":{"x":222,"y":392},"completionTime":5385,"typingTime":4315,"error":false},{"trial":2,"targetString":"toe","userInput":"toe","buttonPosition":{"x":10,"y":292,"zone":"adaptive-circle-border-angle","generationMethod":"adaptive-circle-border-angle-from-calibration","details":{"handedness":"right","circleCenter":{"x":350,"y":700},"radius":488.87217143134666,"radiusCalculationMethod":"70th percentile","radiusPoint":{"x":50,"y":314,"reachable":true,"timestamp":1764047497800},"maxDistance":590.2169092799697,"farthestPoint":{"x":334,"y":110,"reachable":true,"timestamp":1764047498050},"borderThreshold":195.54886857253868,"minBorderDistance":293.323302858808,"maxBorderDistance":527.9819451458544,"selectedBorderPoint":{"x":50,"y":314},"selectedPointDistance":488.87217143134666,"selectedPointAngle":232.1455745753296,"preferredAngleSegment":{"min":207.5,"max":235},"usedSegmentPoints":true,"attemptsToAvoidPrevious":27,"minDistanceFromPrevious":80,"allowedAngleRange":"180-270° (9-12 o'clock)","totalReachablePoints":308,"totalBorderPoints":161,"angleFilteredBorderPoints":161,"validBorderPoints":161}},"buttonTouchPosition":{"x":91,"y":503},"completionTime":2308,"typingTime":1602,"error":false},{"trial":3,"targetString":"roe","userInput":"roe","buttonPosition":{"x":119,"y":370,"zone":"adaptive-circle-border-angle","generationMethod":"adaptive-circle-border-angle-from-calibration","details":{"handedness":"right","circleCenter":{"x":350,"y":700},"radius":488.87217143134666,"radiusCalculationMethod":"70th percentile","radiusPoint":{"x":50,"y":314,"reachable":true,"timestamp":1764047497800},"maxDistance":590.2169092799697,"farthestPoint":{"x":334,"y":110,"reachable":true,"timestamp":1764047498050},"borderThreshold":195.54886857253868,"minBorderDistance":293.323302858808,"maxBorderDistance":527.9819451458544,"selectedBorderPoint":{"x":159,"y":392},"selectedPointDistance":362.41550739448223,"selectedPointAngle":238.19571258920917,"preferredAngleSegment":{"min":235,"max":262.5},"usedSegmentPoints":true,"attemptsToAvoidPrevious":1,"minDistanceFromPrevious":80,"allowedAngleRange":"180-270° (9-12 o'clock)","totalReachablePoints":308,"totalBorderPoints":161,"angleFilteredBorderPoints":161,"validBorderPoints":161}},"buttonTouchPosition":{"x":213,"y":312},"completionTime":2407,"typingTime":1651,"error":false},{"trial":4,"targetString":"foe","userInput":"foe","buttonPosition":{"x":269,"y":244,"zone":"adaptive-circle-border-angle","generationMethod":"adaptive-circle-border-angle-from-calibration","details":{"handedness":"right","circleCenter":{"x":350,"y":700},"radius":488.87217143134666,"radiusCalculationMethod":"70th percentile","radiusPoint":{"x":50,"y":314,"reachable":true,"timestamp":1764047497800},"maxDistance":590.2169092799697,"farthestPoint":{"x":334,"y":110,"reachable":true,"timestamp":1764047498050},"borderThreshold":195.54886857253868,"minBorderDistance":293.323302858808,"maxBorderDistance":527.9819451458544,"selectedBorderPoint":{"x":309,"y":266},"selectedPointDistance":435.9323341987837,"selectedPointAngle":264.6032815378427,"preferredAngleSegment":{"min":262.5,"max":270},"usedSegmentPoints":true,"attemptsToAvoidPrevious":0,"minDistanceFromPrevious":80,"allowedAngleRange":"180-270° (9-12 o'clock)","totalReachablePoints":308,"totalBorderPoints":161,"angleFilteredBorderPoints":161,"validBorderPoints":161}},"buttonTouchPosition":{"x":345,"y":360},"completionTime":2189,"typingTime":1551,"error":false},{"trial":5,"targetString":"rue","userInput":"tue","buttonPosition":{"x":52,"y":371,"zone":"adaptive-circle-border-angle","generationMethod":"adaptive-circle-border-angle-from-calibration","details":{"handedness":"right","circleCenter":{"x":350,"y":700},"radius":488.87217143134666,"radiusCalculationMethod":"70th percentile","radiusPoint":{"x":50,"y":314,"reachable":true,"timestamp":1764047497800},"maxDistance":590.2169092799697,"farthestPoint":{"x":334,"y":110,"reachable":true,"timestamp":1764047498050},"borderThreshold":195.54886857253868,"minBorderDistance":293.323302858808,"maxBorderDistance":527.9819451458544,"selectedBorderPoint":{"x":92,"y":393},"selectedPointDistance":401.0149623143755,"selectedPointAngle":229.95661254239798,"preferredAngleSegment":{"min":180,"max":207.5},"usedSegmentPoints":false,"attemptsToAvoidPrevious":0,"minDistanceFromPrevious":80,"allowedAngleRange":"180-270° (9-12 o'clock)","totalReachablePoints":308,"totalBorderPoints":161,"angleFilteredBorderPoints":161,"validBorderPoints":161}},"buttonTouchPosition":{"x":241,"y":451},"completionTime":2008,"typingTime":1434,"error":true}]},{"condition":"bottom-right","order":3,"avgCompletionTime":2232,"errorRate":0,"trials":[{"trial":1,"targetString":"due","userInput":"due","buttonPosition":{"x":250.6426778764945,"y":553,"zone":"bottom-randomized","generationMethod":"bottom-random-x-full-width","details":{"areaWidth":389,"areaHeight":647,"minX":10,"maxX":299,"fixedY":553,"randomizedX":250.6426778764945,"range":"0-100% screen width"}},"buttonTouchPosition":{"x":229,"y":592},"completionTime":2409,"typingTime":1584,"error":false},{"trial":2,"targetString":"awe","userInput":"awe","buttonPosition":{"x":203.704703018919,"y":553,"zone":"bottom-randomized","generationMethod":"bottom-random-x-full-width","details":{"areaWidth":389,"areaHeight":647,"minX":10,"maxX":299,"fixedY":553,"randomizedX":203.704703018919,"range":"0-100% screen width"}},"buttonTouchPosition":{"x":128,"y":581},"completionTime":2474,"typingTime":1800,"error":false},{"trial":3,"targetString":"owe","userInput":"owe","buttonPosition":{"x":103.87666595245065,"y":553,"zone":"bottom-randomized","generationMethod":"bottom-random-x-full-width","details":{"areaWidth":389,"areaHeight":647,"minX":10,"maxX":299,"fixedY":553,"randomizedX":103.87666595245065,"range":"0-100% screen width"}},"buttonTouchPosition":{"x":277,"y":593},"completionTime":2192,"typingTime":1634,"error":false},{"trial":4,"targetString":"ewe","userInput":"ewe","buttonPosition":{"x":27.11844813211103,"y":553,"zone":"bottom-randomized","generationMethod":"bottom-random-x-full-width","details":{"areaWidth":389,"areaHeight":647,"minX":10,"maxX":299,"fixedY":553,"randomizedX":27.11844813211103,"range":"0-100% screen width"}},"buttonTouchPosition":{"x":362,"y":580},"completionTime":2041,"typingTime":1467,"error":false},{"trial":5,"targetString":"eye","userInput":"eye","buttonPosition":{"x":290.26421783369295,"y":553,"zone":"bottom-randomized","generationMethod":"bottom-random-x-full-width","details":{"areaWidth":389,"areaHeight":647,"minX":10,"maxX":299,"fixedY":553,"randomizedX":290.26421783369295,"range":"0-100% screen width"}},"buttonTouchPosition":{"x":240,"y":599},"completionTime":2044,"typingTime":1470,"error":false}]}]}